README
setup.py
openproximity_plugin_remotecontrol.egg-info/PKG-INFO
openproximity_plugin_remotecontrol.egg-info/SOURCES.txt
openproximity_plugin_remotecontrol.egg-info/dependency_links.txt
openproximity_plugin_remotecontrol.egg-info/top_level.txt
remotesupport/__init__.py
remotesupport/plugin.py
remotesupport/urls.py
remotesupport/views.py
remotesupport/static/js/remotecontrol.js
remotesupport/templates/remotesupport/base.html
remotesupport/templates/remotesupport/index.html