Metadata-Version: 1.0
Name: openproximity-plugin-remotecontrol
Version: 0.1.0
Summary: A plugin that allows customers to get remote support
Home-page: https://github.com/OpenProximity/plugins-remotecontrol
Author: Naranjo Manuel Francisco
Author-email: manuel@aircable.net
License: GPL2
Platform: UNKNOWN
